duckdb_ext/__init__.py
duckdb_ext/duckdb_ext.py
duckdb_ext/py.typed
duckdb_ext-0.1.2.dist-info/licenses/LICENSE
duckdb_ext-0.1.2.dist-info/METADATA
duckdb_ext-0.1.2.dist-info/WHEEL
duckdb_ext-0.1.2.dist-info/top_level.txt
duckdb_ext-0.1.2.dist-info/RECORD
